setup.py
anillo_auth/__init__.py
anillo_auth/auth.py
anillo_auth/exceptions.py
anillo_auth/utils.py
anillo_auth.egg-info/PKG-INFO
anillo_auth.egg-info/SOURCES.txt
anillo_auth.egg-info/dependency_links.txt
anillo_auth.egg-info/requires.txt
anillo_auth.egg-info/top_level.txt
anillo_auth/backends/__init__.py
anillo_auth/backends/http_auth.py
anillo_auth/backends/session.py
anillo_auth/backends/token.py